reframe.py
reframe-1.0.1.dist-info/DESCRIPTION.rst
reframe-1.0.1.dist-info/METADATA
reframe-1.0.1.dist-info/RECORD
reframe-1.0.1.dist-info/WHEEL
reframe-1.0.1.dist-info/metadata.json
reframe-1.0.1.dist-info/top_level.txt
