Metadata-Version: 2.0
Name: reframe
Version: 1.0.1
Summary: Relational algebra on top of Pandas DataFrames 
Home-page: https://github.com/bnmnetp/reframe
Author: Brad Miller
Author-email: bonelake@mac.com
License: GPL
Keywords: database,relational
Platform: UNKNOWN
Requires-Dist: pandas (>=0.16.0)
